{
    "file_format_version" : "1.4.0",
    "layer": {
        "name": "VK_LAYER_LUNARG_device_simulation",
        "type": "GLOBAL",
        "library_path": ".\\VkLayer_device_simulation.dll",
        "api_version": "1.1.130",
        "implementation_version": "1.2.6",
        "description": "LunarG device simulation layer",
        "device_extensions": [
            {
                "name": "VK_EXT_tooling_info",
                "spec_version": "1",
                "entrypoints": [
                    "vkGetPhysicalDeviceToolPropertiesEXT"
                ]
            }
        ],
        "settings": [
            {
                "key": "filename",
                "env": "VK_DEVSIM_FILENAME",
                "label": "Devsim JSON configuration file",
                "description": "Path of a devsim configuration file to load.",
                "type": "LOAD_FILE",
                "filter": "*.json",
                "default": ""
            },
            {
                "key": "debug_enable",
                "env": "VK_DEVSIM_DEBUG_ENABLE",
                "label": "Debug Enable",
                "description": "Enables debug message output.",
                "type": "BOOL_NUMERIC",
                "default": true
            },
            {
                "key": "exit_on_error",
                "env": "VK_DEVSIM_EXIT_ON_ERROR",
                "label": "Exit on Error",
                "description": "Enables exit-on-error.",
                "type": "BOOL_NUMERIC",
                "default": false
            }
        ]
    }
}
